yajaw/__about__.py
yajaw/__init__.py
yajaw/configuration.py
yajaw/exceptions.py
yajaw/jira.py
yajaw/core/__init__.py
yajaw/core/rest.py
yajaw/utils/__init__.py
yajaw/utils/concurrency.py
yajaw/utils/performance.py
yajaw-0.1.0.dev2.dist-info/METADATA
yajaw-0.1.0.dev2.dist-info/WHEEL
yajaw-0.1.0.dev2.dist-info/licenses/LICENSE
yajaw-0.1.0.dev2.dist-info/RECORD
