Metadata-Version: 2.1
Name: yajaw
Version: 0.1.0.dev2
Summary: Yet Another Jira API Wrapper
Project-URL: Documentation, https://yajaw.readthedocs.io/
Project-URL: Issues, https://github.com/unknown/rmrighes/issues
Project-URL: Source, https://github.com/rmrighes/yajaw
Author-email: rmrighes <rmrighes@users.noreply.github.com>
License-Expression: MIT
License-File: LICENSE
Keywords: api,jira
Classifier: Development Status :: 1 - Planning
Classifier: Programming Language :: Python
Classifier: Programming Language :: Python :: 3.11
Classifier: Programming Language :: Python :: 3.12
Requires-Python: >=3.11
Requires-Dist: asyncio
Requires-Dist: httpx
